vaultkeeper/__init__.py
vaultkeeper/configparser.py
vaultkeeper/secret.py
vaultkeeper/vaultkeeper.py
vaultkeeper/tests/__init__.py
vaultkeeper/tests/fake_gatekeeper.py
vaultkeeper/tests/fake_vault.py
vaultkeeper/tests/test_fakegatekeeper.py
vaultkeeper/tests/test_fakevault.py
vaultkeeper/tests/test_secrets.py
vaultkeeper/tests/test_vaultkeeper.py
vaultkeeper-0.0.2.dist-info/DESCRIPTION.rst
vaultkeeper-0.0.2.dist-info/METADATA
vaultkeeper-0.0.2.dist-info/RECORD
vaultkeeper-0.0.2.dist-info/WHEEL
vaultkeeper-0.0.2.dist-info/dependency_links.txt
vaultkeeper-0.0.2.dist-info/entry_points.txt
vaultkeeper-0.0.2.dist-info/metadata.json
vaultkeeper-0.0.2.dist-info/top_level.txt
