Metadata-Version: 2.0
Name: vaultkeeper
Version: 0.0.2
Summary: An agent that works with vault-gatekeeper-mesos to fetch and renew Vault credentials.
Home-page: https://github.com/praekeltfoundation/vaultkeeper
Author: mracter
Author-email: mary@praekelt.org
License: BSD
Platform: UNKNOWN
Requires-Dist: hvac (>=0.2.17)
Requires-Dist: requests
Requires-Dist: subprocess32
Provides-Extra: test
Requires-Dist: pytest (>=3.0.0); extra == 'test'
Requires-Dist: pytest-cov; extra == 'test'
Requires-Dist: responses; extra == 'test'
